drf_nested_forms/__init__.py
drf_nested_forms/exceptions.py
drf_nested_forms/helpers.py
drf_nested_forms/mixins.py
drf_nested_forms/parsers.py
drf_nested_forms/settings.py
drf_nested_forms/utils.py
drf_nested_forms-1.1.8.dist-info/LICENSE
drf_nested_forms-1.1.8.dist-info/METADATA
drf_nested_forms-1.1.8.dist-info/WHEEL
drf_nested_forms-1.1.8.dist-info/top_level.txt
drf_nested_forms-1.1.8.dist-info/RECORD
