Metadata-Version: 2.1
Name: drf_nested_forms
Version: 1.1.8
Summary: A library that parses nested json or form data to python object
Home-page: http://github.com/emperorDuke/nested_formdata
Download-URL: http://github.com/emperorDuke/nested_formdata/archive/v1.1.8.tar.gz
Author: Duke Effiom
Author-email: effiomduke@gmail.com
License: MIT
Keywords: drf,nested form,html_formsdrf_nested_forms,restframework,nested json
Classifier: Environment :: Web Environment
Classifier: Framework :: Django
Classifier: Framework :: Django :: 2.0
Classifier: Framework :: Django :: 2.1
Classifier: Framework :: Django :: 2.2
Classifier: Framework :: Django :: 3.2
Classifier: Framework :: Django :: 4.2
Classifier: Intended Audience :: Developers
Classifier: Operating System :: OS Independent
Classifier: Programming Language :: Python
Classifier: Programming Language :: Python :: 3.5
Classifier: Programming Language :: Python :: 3.6
Classifier: Programming Language :: Python :: 3.7
Classifier: Programming Language :: Python :: 3.8
Classifier: Programming Language :: Python :: 3.9
Classifier: Programming Language :: Python :: 3.10
Classifier: Programming Language :: Python :: 3.11
Classifier: Topic :: Internet :: WWW/HTTP
Classifier: License :: OSI Approved :: MIT License
License-File: LICENSE
